bio2bel_uniprot/__init__.py
bio2bel_uniprot/constants.py
bio2bel_uniprot/parser.py
bio2bel_uniprot-0.0.2.dist-info/LICENSE
bio2bel_uniprot-0.0.2.dist-info/METADATA
bio2bel_uniprot-0.0.2.dist-info/WHEEL
bio2bel_uniprot-0.0.2.dist-info/entry_points.txt
bio2bel_uniprot-0.0.2.dist-info/top_level.txt
bio2bel_uniprot-0.0.2.dist-info/RECORD
