Metadata-Version: 2.1
Name: bio2bel-uniprot
Version: 0.0.2
Summary: A package for downloading, parsing, storing, and serializing UniProt
Home-page: https://github.com/bio2bel/uniprot
Author: Charles Tapley Hoyt
Author-email: charles.hoyt@scai.fraunhofer.de
Maintainer: Charles Tapley Hoyt
Maintainer-email: charles.hoyt@scai.fraunhofer.de
License: MIT License
Keywords: Biological Expression Language,BEL,Systems Biology,Networks Biology,InterPro
Platform: UNKNOWN
Classifier: Development Status :: 4 - Beta
Classifier: Environment :: Console
Classifier: Intended Audience :: Developers
Classifier: Intended Audience :: Science/Research
Classifier: License :: OSI Approved :: MIT License
Classifier: Operating System :: OS Independent
Classifier: Programming Language :: Python
Classifier: Programming Language :: Python :: 3.6
Classifier: Topic :: Scientific/Engineering :: Bio-Informatics
Requires-Dist: bio2bel
Requires-Dist: pandas
